mem_brain_mcp/__init__.py
mem_brain_mcp/__main__.py
mem_brain_mcp/client.py
mem_brain_mcp/config.py
mem_brain_mcp/server.py
mem_brain_mcp-1.0.8.dist-info/METADATA
mem_brain_mcp-1.0.8.dist-info/WHEEL
mem_brain_mcp-1.0.8.dist-info/entry_points.txt
mem_brain_mcp-1.0.8.dist-info/RECORD
